commerce_shopper_products/__init__.py
commerce_shopper_products/_base_client.py
commerce_shopper_products/_client.py
commerce_shopper_products/_compat.py
commerce_shopper_products/_constants.py
commerce_shopper_products/_exceptions.py
commerce_shopper_products/_files.py
commerce_shopper_products/_models.py
commerce_shopper_products/_qs.py
commerce_shopper_products/_resource.py
commerce_shopper_products/_response.py
commerce_shopper_products/_streaming.py
commerce_shopper_products/_types.py
commerce_shopper_products/_version.py
commerce_shopper_products/py.typed
commerce_shopper_products/_utils/__init__.py
commerce_shopper_products/_utils/_compat.py
commerce_shopper_products/_utils/_datetime_parse.py
commerce_shopper_products/_utils/_logs.py
commerce_shopper_products/_utils/_proxy.py
commerce_shopper_products/_utils/_reflection.py
commerce_shopper_products/_utils/_resources_proxy.py
commerce_shopper_products/_utils/_streams.py
commerce_shopper_products/_utils/_sync.py
commerce_shopper_products/_utils/_transform.py
commerce_shopper_products/_utils/_typing.py
commerce_shopper_products/_utils/_utils.py
commerce_shopper_products/lib/.keep
commerce_shopper_products/resources/__init__.py
commerce_shopper_products/resources/organizations/__init__.py
commerce_shopper_products/resources/organizations/categories.py
commerce_shopper_products/resources/organizations/organizations.py
commerce_shopper_products/resources/organizations/products.py
commerce_shopper_products/types/__init__.py
commerce_shopper_products/types/organizations/__init__.py
commerce_shopper_products/types/organizations/bundled_product.py
commerce_shopper_products/types/organizations/category.py
commerce_shopper_products/types/organizations/category_list_params.py
commerce_shopper_products/types/organizations/category_list_response.py
commerce_shopper_products/types/organizations/category_retrieve_params.py
commerce_shopper_products/types/organizations/image.py
commerce_shopper_products-0.1.0.dist-info/METADATA
commerce_shopper_products-0.1.0.dist-info/WHEEL
commerce_shopper_products-0.1.0.dist-info/licenses/LICENSE
commerce_shopper_products-0.1.0.dist-info/RECORD
